{
	"info": {
		"_postman_id": "6462933b-8fda-4d83-aee2-9fa9c3c90974",
		"name": "[ApiTarefa]",
		"schema": "https://schema.getpostman.com/json/collection/v2.1.0/collection.json",
		"_exporter_id": "28626452"
	},
	"item": [
		{
			"name": "listar tarefas",
			"request": {
				"method": "GET",
				"header": [],
				"url": {
					"raw": "http://localhost:8081/tarefa/all",
					"protocol": "http",
					"host": [
						"localhost"
					],
					"port": "8081",
					"path": [
						"tarefa",
						"all"
					]
				}
			},
			"response": []
		},
		{
			"name": "listar tarefa  id",
			"request": {
				"method": "GET",
				"header": [],
				"url": {
					"raw": "http://localhost:8081/tarefa/all/1",
					"protocol": "http",
					"host": [
						"localhost"
					],
					"port": "8081",
					"path": [
						"tarefa",
						"all",
						"1"
					]
				}
			},
			"response": []
		},
		{
			"name": "criar tarefa",
			"request": {
				"method": "POST",
				"header": [],
				"body": {
					"mode": "raw",
					"raw": "    {\n        \"descricao\": \"limpar o quintal\",\n        \"status\": \"concluido\"\n    }",
					"options": {
						"raw": {
							"language": "json"
						}
					}
				},
				"url": {
					"raw": "http://localhost:8081/tarefa/criar",
					"protocol": "http",
					"host": [
						"localhost"
					],
					"port": "8081",
					"path": [
						"tarefa",
						"criar"
					]
				}
			},
			"response": []
		},
		{
			"name": "editar tarefa",
			"request": {
				"method": "PUT",
				"header": [],
				"url": {
					"raw": "http://localhost:8081/tarefa/editar",
					"protocol": "http",
					"host": [
						"localhost"
					],
					"port": "8081",
					"path": [
						"tarefa",
						"editar"
					]
				}
			},
			"response": []
		},
		{
			"name": "excluir tarefa",
			"request": {
				"method": "DELETE",
				"header": [],
				"url": {
					"raw": "http://localhost:8081/tarefa/delete/id/1",
					"protocol": "http",
					"host": [
						"localhost"
					],
					"port": "8081",
					"path": [
						"tarefa",
						"delete",
						"id",
						"1"
					]
				}
			},
			"response": []
		}
	]
}